pyppbox_torchreid/__init__.py
pyppbox_torchreid/metrics/__init__.py
pyppbox_torchreid/metrics/distance.py
pyppbox_torchreid/metrics/accuracy.py
pyppbox_torchreid/metrics/rank.py
pyppbox_torchreid/metrics/rank_cylib/__init__.py
pyppbox_torchreid/metrics/rank_cylib/test_cython.py
pyppbox_torchreid/metrics/rank_cylib/rank_cy.cpython-310-darwin.so
pyppbox_torchreid/losses/__init__.py
pyppbox_torchreid/losses/hard_mine_triplet_loss.py
pyppbox_torchreid/losses/cross_entropy_loss.py
pyppbox_torchreid/optim/lr_scheduler.py
pyppbox_torchreid/optim/__init__.py
pyppbox_torchreid/optim/radam.py
pyppbox_torchreid/optim/optimizer.py
pyppbox_torchreid/utils/rerank.py
pyppbox_torchreid/utils/model_complexity.py
pyppbox_torchreid/utils/loggers.py
pyppbox_torchreid/utils/reidtools.py
pyppbox_torchreid/utils/tools.py
pyppbox_torchreid/utils/__init__.py
pyppbox_torchreid/utils/avgmeter.py
pyppbox_torchreid/utils/feature_extractor.py
pyppbox_torchreid/utils/torchtools.py
pyppbox_torchreid/models/shufflenetv2.py
pyppbox_torchreid/models/mlfn.py
pyppbox_torchreid/models/resnet_ibn_b.py
pyppbox_torchreid/models/mudeep.py
pyppbox_torchreid/models/squeezenet.py
pyppbox_torchreid/models/senet.py
pyppbox_torchreid/models/pcb.py
pyppbox_torchreid/models/densenet.py
pyppbox_torchreid/models/__init__.py
pyppbox_torchreid/models/osnet_ain.py
pyppbox_torchreid/models/inceptionv4.py
pyppbox_torchreid/models/base_model.py
pyppbox_torchreid/models/resnetmid.py
pyppbox_torchreid/models/osnet.py
pyppbox_torchreid/models/shufflenet.py
pyppbox_torchreid/models/resnet.py
pyppbox_torchreid/models/mobilenetv2.py
pyppbox_torchreid/models/inceptionresnetv2.py
pyppbox_torchreid/models/xception.py
pyppbox_torchreid/models/nasnet.py
pyppbox_torchreid/models/hacnn.py
pyppbox_torchreid/models/resnet_ibn_a.py
pyppbox_torchreid/data/transforms.py
pyppbox_torchreid/data/__init__.py
pyppbox_torchreid/data/sampler.py
pyppbox_torchreid/data/datamanager.py
pyppbox_torchreid-1.4.1.0.dist-info/RECORD
pyppbox_torchreid-1.4.1.0.dist-info/LICENSE
pyppbox_torchreid-1.4.1.0.dist-info/WHEEL
pyppbox_torchreid-1.4.1.0.dist-info/top_level.txt
pyppbox_torchreid-1.4.1.0.dist-info/METADATA
