Metadata-Version: 2.2
Name: pyppbox-torchreid
Version: 1.4.1.0
Summary: Customized Torchreid for pyppbox: Deep learning person re-identification.
Home-page: https://github.com/rathaumons/torchreid-for-pyppbox
Author: Ratha SIV
Maintainer: rathaROG
License: MIT
Keywords: Person Re-Identification,Deep Learning,pyppbox
Classifier: Development Status :: 4 - Beta
Classifier: Environment :: Console
Classifier: Intended Audience :: Developers
Classifier: Intended Audience :: Education
Classifier: Intended Audience :: Information Technology
Classifier: Intended Audience :: Science/Research
Classifier: License :: OSI Approved :: MIT License
Classifier: Programming Language :: Python :: 3
Classifier: Programming Language :: Python :: 3.8
Classifier: Programming Language :: Python :: 3.9
Classifier: Programming Language :: Python :: 3.10
Classifier: Programming Language :: Python :: 3.11
Classifier: Programming Language :: Python :: 3.12
Classifier: Programming Language :: Python :: 3.13
Classifier: Topic :: Education
Classifier: Topic :: Education :: Testing
Classifier: Topic :: Scientific/Engineering
Classifier: Topic :: Scientific/Engineering :: Image Recognition
Classifier: Topic :: Scientific/Engineering :: Information Analysis
Classifier: Topic :: Software Development
Classifier: Topic :: Software Development :: Libraries
Classifier: Operating System :: Microsoft :: Windows
Classifier: Operating System :: POSIX
Classifier: Operating System :: Unix
Classifier: Operating System :: MacOS
Requires-Python: >=3.8
License-File: LICENSE
Requires-Dist: Cython>=0.29.32
Requires-Dist: numpy>=1.23.5
Requires-Dist: h5py
Requires-Dist: Pillow
Requires-Dist: six
Requires-Dist: scipy>=1.10.0
Requires-Dist: matplotlib
Requires-Dist: tensorboard
Requires-Dist: torch
Requires-Dist: torchvision
Requires-Dist: future
Requires-Dist: yacs
Requires-Dist: gdown
Requires-Dist: yapf
Requires-Dist: isort
Requires-Dist: imageio
Requires-Dist: chardet
Dynamic: author
Dynamic: classifier
Dynamic: description
Dynamic: description-content-type
Dynamic: home-page
Dynamic: keywords
Dynamic: license
Dynamic: maintainer
Dynamic: requires-dist
Dynamic: requires-python
Dynamic: summary
